sofascrape/__init__.py
sofascrape/client.py
sofascrape/models.py
sofascrape/utils.py
sofascrape-0.1.2.dist-info/licenses/LICENSE
sofascrape-0.1.2.dist-info/METADATA
sofascrape-0.1.2.dist-info/WHEEL
sofascrape-0.1.2.dist-info/top_level.txt
sofascrape-0.1.2.dist-info/RECORD
