Metadata-Version: 2.4
Name: sofascrape
Version: 0.1.2
Summary: A Python library for scraping and interacting with SofaScore APIs
Author-email: Chumari <dchumari@gmail.com>
License: MIT License
Project-URL: Homepage, https://github.com/dchumari/sofascrape
Project-URL: Repository, https://github.com/dchumari/sofascrape.git
Project-URL: Bug Reports, https://github.com/dchumari/sofascrape/issues
Keywords: sofascore,scraping,sports,football,api
Classifier: Development Status :: 3 - Alpha
Classifier: Intended Audience :: Developers
Classifier: Programming Language :: Python :: 3
Classifier: Programming Language :: Python :: 3.7
Classifier: Programming Language :: Python :: 3.8
Classifier: Programming Language :: Python :: 3.9
Classifier: Programming Language :: Python :: 3.10
Classifier: Programming Language :: Python :: 3.11
Requires-Python: >=3.7
License-File: LICENSE
Requires-Dist: playwright>=1.30.0
Requires-Dist: beautifulsoup4>=4.11.0
Requires-Dist: requests>=2.28.0
Provides-Extra: dev
Requires-Dist: pytest>=6.0; extra == "dev"
Requires-Dist: pytest-cov; extra == "dev"
Requires-Dist: black; extra == "dev"
Requires-Dist: flake8; extra == "dev"
Requires-Dist: mypy; extra == "dev"
Dynamic: license-file
